kithara/__init__.py
kithara/callbacks/__init__.py
kithara/callbacks/checkpointer.py
kithara/callbacks/profiler.py
kithara/config/__init__.py
kithara/config/default.yaml
kithara/config/pyconfig.py
kithara/dataset/__init__.py
kithara/dataset/dataloader.py
kithara/dataset/dataset.py
kithara/dataset/packed_dataset.py
kithara/dataset/sft.py
kithara/dataset/text_completion.py
kithara/dataset/utils.py
kithara/distributed/__init__.py
kithara/distributed/data/__init__.py
kithara/distributed/data/split.py
kithara/distributed/sharding/__init__.py
kithara/distributed/sharding/_data_sharding.py
kithara/distributed/sharding/_layout.py
kithara/distributed/sharding/_mesh.py
kithara/distributed/sharding/maxtext.py
kithara/distributed/sharding/strategy.py
kithara/distributed/sharding/utils.py
kithara/distributed/sharding/models/__init__.py
kithara/distributed/sharding/models/gemma.py
kithara/distributed/sharding/models/llama.py
kithara/model/README.md
kithara/model/__init__.py
kithara/model/model.py
kithara/model/supported_models.py
kithara/model/hf_compatibility/__init__.py
kithara/model/hf_compatibility/model_configs.py
kithara/model/hf_compatibility/shape_mapping.py
kithara/model/hf_compatibility/to_huggingface.py
kithara/model/kerashub/__init__.py
kithara/model/kerashub/keras_hub_model.py
kithara/model/kerashub/ckpt_compatibility/param_mapping.py
kithara/model/kerashub/ckpt_compatibility/to_huggingface.py
kithara/model/maxtext/__init__.py
kithara/model/maxtext/conversion_utils.py
kithara/model/maxtext/inference_engine.py
kithara/model/maxtext/maxtext_model.py
kithara/model/maxtext/JetStream/.git
kithara/model/maxtext/JetStream/.gitattributes
kithara/model/maxtext/JetStream/.gitignore
kithara/model/maxtext/JetStream/AUTHORS
kithara/model/maxtext/JetStream/CONTRIBUTING.md
kithara/model/maxtext/JetStream/LICENSE
kithara/model/maxtext/JetStream/MANIFEST.in
kithara/model/maxtext/JetStream/Makefile
kithara/model/maxtext/JetStream/README.md
kithara/model/maxtext/JetStream/google_jetstream.egg-info/PKG-INFO
kithara/model/maxtext/JetStream/google_jetstream.egg-info/SOURCES.txt
kithara/model/maxtext/JetStream/google_jetstream.egg-info/dependency_links.txt
kithara/model/maxtext/JetStream/google_jetstream.egg-info/requires.txt
kithara/model/maxtext/JetStream/google_jetstream.egg-info/top_level.txt
kithara/model/maxtext/maxtext/MaxText/MaxText.egg-info/PKG-INFO
kithara/model/maxtext/maxtext/MaxText/MaxText.egg-info/SOURCES.txt
kithara/model/maxtext/maxtext/MaxText/MaxText.egg-info/dependency_links.txt
kithara/model/maxtext/maxtext/MaxText/MaxText.egg-info/requires.txt
kithara/model/maxtext/maxtext/MaxText/MaxText.egg-info/top_level.txt
kithara-0.0.10.dist-info/licenses/LICENSE
kithara-0.0.10.dist-info/WHEEL
kithara-0.0.10.dist-info/METADATA
kithara-0.0.10.dist-info/RECORD
