Metadata-Version: 2.4
Name: kithara
Version: 0.0.10
Summary: LLM post-training library
Author: Kithara Authors
Requires-Python: >= 3.11
License-File: LICENSE
Requires-Dist: flax>=0.7.0
Requires-Dist: datasets
Requires-Dist: huggingface-hub
Requires-Dist: keras>=3.8.0
Requires-Dist: transformers>=4.45.1
Requires-Dist: keras-hub>=0.18.1
Requires-Dist: google-api-python-client
Requires-Dist: google-auth-httplib2
Requires-Dist: google-auth-oauthlib
Requires-Dist: ray[default]==2.40.0
Requires-Dist: jax[cpu]
Requires-Dist: peft
Requires-Dist: hf_transfer
Requires-Dist: tabulate
Requires-Dist: cryptography
Requires-Dist: huggingface_hub
Requires-Dist: aqtp
Requires-Dist: grain-nightly
Requires-Dist: orbax-checkpoint>=0.10.3
Requires-Dist: google-cloud-logging
Requires-Dist: tensorboardx
Requires-Dist: ml-collections
Requires-Dist: tensorflow_datasets
Requires-Dist: sentencepiece
Requires-Dist: tiktoken
Requires-Dist: cloud-accelerator-diagnostics
Requires-Dist: cloud-tpu-diagnostics
Requires-Dist: ml-goodput-measurement
Requires-Dist: google-cloud-monitoring
Requires-Dist: omegaconf
Requires-Dist: setuptools==61.0
Requires-Dist: jaxtyping
Requires-Dist: clu
Requires-Dist: editdistance
Requires-Dist: pyglove
Requires-Dist: tensorflow_datasets
Requires-Dist: tfds-nightly
Requires-Dist: jax[cpu] ; extra == "cpu"
Requires-Dist: torch==2.4.0 ; extra == "cpu"
Requires-Dist: twine ; extra == "dev"
Requires-Dist: flit ; extra == "dev"
Requires-Dist: sphinx==8.2.0 ; extra == "dev"
Requires-Dist: sphinx-autobuild ; extra == "dev"
Requires-Dist: sphinxawesome-theme>=5.3.2 ; extra == "dev"
Requires-Dist: sphinx_design ; extra == "dev"
Requires-Dist: jax[cuda] ; extra == "gpu"
Requires-Dist: torch==2.4.0 ; extra == "gpu"
Requires-Dist: jax[tpu] ; extra == "tpu"
Requires-Dist: torch==2.4.0+cpu ; extra == "tpu"
Project-URL: Documentation, https://kithara.readthedocs.io/en/latest/index.html
Project-URL: Homepage, https://github.com/AI-Hypercomputer/kithara
Project-URL: Repository, https://github.com/AI-Hypercomputer/kithara
Provides-Extra: cpu
Provides-Extra: dev
Provides-Extra: gpu
Provides-Extra: tpu
